pyloggerhelper/__init__.py
pyloggerhelper/proxy.py
pyloggerhelper-0.0.4.dist-info/LICENSE
pyloggerhelper-0.0.4.dist-info/METADATA
pyloggerhelper-0.0.4.dist-info/WHEEL
pyloggerhelper-0.0.4.dist-info/top_level.txt
pyloggerhelper-0.0.4.dist-info/RECORD
