Metadata-Version: 2.1
Name: pyloggerhelper
Version: 0.0.4
Summary: json logger helper
Author: hsz
Author-email: hsz1273327@gmail.com
License: MIT License
Keywords: logger,proxy
Classifier: License :: OSI Approved :: MIT License
Classifier: Programming Language :: Python :: 3.8
Classifier: Programming Language :: Python :: 3.9
Classifier: Programming Language :: Python :: 3.10
Classifier: Programming Language :: Python :: 3.11
License-File: LICENSE
Requires-Dist: pyproxypattern (>=0.0.1)
Requires-Dist: structlog (>=21.1.0)
